rest_tools/__init__.py
rest_tools/py.typed
rest_tools/telemetry.py
rest_tools/client/__init__.py
rest_tools/client/client.py
rest_tools/client/client_credentials.py
rest_tools/client/device_client.py
rest_tools/client/openid_client.py
rest_tools/client/session.py
rest_tools/client/utils.py
rest_tools/server/__init__.py
rest_tools/server/arghandler.py
rest_tools/server/decorators.py
rest_tools/server/handler.py
rest_tools/server/server.py
rest_tools/server/session.py
rest_tools/server/stats.py
rest_tools/utils/__init__.py
rest_tools/utils/auth.py
rest_tools/utils/config.py
rest_tools/utils/daemon.py
rest_tools/utils/json_util.py
rest_tools/utils/pkce.py
wipac_rest_tools-1.12.3.dist-info/licenses/LICENSE
wipac_rest_tools-1.12.3.dist-info/METADATA
wipac_rest_tools-1.12.3.dist-info/WHEEL
wipac_rest_tools-1.12.3.dist-info/top_level.txt
wipac_rest_tools-1.12.3.dist-info/RECORD
