Metadata-Version: 2.4
Name: wipac-rest-tools
Version: 1.12.3
Summary: REST tools in python - common code for client and server
Author-email: WIPAC Developers <developers@icecube.wisc.edu>
License-Expression: MIT
Project-URL: Homepage, https://pypi.org/project/wipac-rest-tools/
Project-URL: Tracker, https://github.com/WIPACrepo/rest-tools/issues
Project-URL: Source, https://github.com/WIPACrepo/rest-tools
Keywords: WIPAC,IceCube,REST,tools,utilities
Classifier: Programming Language :: Python :: 3.10
Classifier: Programming Language :: Python :: 3.11
Classifier: Programming Language :: Python :: 3.12
Classifier: Programming Language :: Python :: 3.13
Classifier: Programming Language :: Python :: 3.14
Requires-Python: <3.15,>=3.10
License-File: LICENSE
Requires-Dist: cachetools
Requires-Dist: pyjwt[crypto]!=2.6.0
Requires-Dist: qrcode
Requires-Dist: requests
Requires-Dist: requests-futures
Requires-Dist: tornado
Requires-Dist: urllib3>=2.0.4
Requires-Dist: wipac-dev-tools
Provides-Extra: openapi
Requires-Dist: openapi-core; extra == "openapi"
Provides-Extra: redis
Requires-Dist: redis[hiredis]; extra == "redis"
Provides-Extra: tests
Requires-Dist: httpretty; extra == "tests"
Requires-Dist: pycycle; extra == "tests"
Requires-Dist: pytest; extra == "tests"
Requires-Dist: pytest-asyncio; extra == "tests"
Requires-Dist: pytest-cov; extra == "tests"
Requires-Dist: pytest-mock; extra == "tests"
Requires-Dist: redis[hiredis]; extra == "tests"
Requires-Dist: requests-mock; extra == "tests"
Requires-Dist: types-requests; extra == "tests"
Provides-Extra: mypy
Requires-Dist: httpretty; extra == "mypy"
Requires-Dist: openapi-core; extra == "mypy"
Requires-Dist: pycycle; extra == "mypy"
Requires-Dist: pytest; extra == "mypy"
Requires-Dist: pytest-asyncio; extra == "mypy"
Requires-Dist: pytest-cov; extra == "mypy"
Requires-Dist: pytest-mock; extra == "mypy"
Requires-Dist: redis[hiredis]; extra == "mypy"
Requires-Dist: requests-mock; extra == "mypy"
Requires-Dist: types-requests; extra == "mypy"
Dynamic: license-file
